pyrandyos/__init__.py
pyrandyos/__main__.py
pyrandyos/_version.py
pyrandyos/app.py
pyrandyos/logging.py
pyrandyos/version.py
pyrandyos/_testing/__init__.py
pyrandyos/_testing/_pyrandyos_testing.py
pyrandyos/_testing/debug.py
pyrandyos/config/__init__.py
pyrandyos/config/appconfig.py
pyrandyos/config/defaults.py
pyrandyos/config/expandutils.py
pyrandyos/config/keys.py
pyrandyos/config/local.py
pyrandyos/gui/__init__.py
pyrandyos/gui/callback.py
pyrandyos/gui/gui_app.py
pyrandyos/gui/loadstatus.py
pyrandyos/gui/qrc.py
pyrandyos/gui/qt.py
pyrandyos/gui/splash.py
pyrandyos/gui/utils.py
pyrandyos/gui/window.py
pyrandyos/gui/dialogs/__init__.py
pyrandyos/gui/dialogs/config/__init__.py
pyrandyos/gui/dialogs/config/icons.py
pyrandyos/gui/dialogs/config/pres.py
pyrandyos/gui/dialogs/config/view.py
pyrandyos/gui/dialogs/log/__init__.py
pyrandyos/gui/dialogs/log/mixin.py
pyrandyos/gui/dialogs/log/pres.py
pyrandyos/gui/dialogs/log/view.py
pyrandyos/gui/icons/__init__.py
pyrandyos/gui/icons/init_template.py
pyrandyos/gui/icons/update_from_spec.py
pyrandyos/gui/icons/utils.py
pyrandyos/gui/icons/assets/.gitattributes
pyrandyos/gui/icons/assets/Codicons/charmap/LICENSE
pyrandyos/gui/icons/assets/Codicons/charmap/LICENSE-CODE
pyrandyos/gui/icons/assets/Codicons/charmap/mapping.json
pyrandyos/gui/icons/assets/Codicons/ttf/LICENSE.txt
pyrandyos/gui/icons/assets/Codicons/ttf/codicon.ttf
pyrandyos/gui/icons/assets/ElusiveIcons/charmap/LICENSE.txt
pyrandyos/gui/icons/assets/ElusiveIcons/charmap/elusiveicons-webfont-charmap-2.0.json
pyrandyos/gui/icons/assets/ElusiveIcons/ttf/LICENSE.txt
pyrandyos/gui/icons/assets/ElusiveIcons/ttf/elusiveicons-webfont-2.0.ttf
pyrandyos/gui/icons/assets/Fa5/charmap/LICENSE.txt
pyrandyos/gui/icons/assets/Fa5/charmap/fontawesome5-regular-webfont-charmap-5.15.4.json
pyrandyos/gui/icons/assets/Fa5/ttf/LICENSE.txt
pyrandyos/gui/icons/assets/Fa5/ttf/fontawesome5-regular-webfont-5.15.4.ttf
pyrandyos/gui/icons/assets/Fa5_Brands/charmap/LICENSE.txt
pyrandyos-1.2.1.dist-info/METADATA
pyrandyos-1.2.1.dist-info/WHEEL
pyrandyos-1.2.1.dist-info/licenses/LICENSE
pyrandyos-1.2.1.dist-info/RECORD
