Metadata-Version: 2.4
Name: pyrandyos
Version: 1.2.1
Summary: Library of common functions for Python applications
Project-URL: Homepage, https://github.com/emanspeaks/pyrandyos
Project-URL: Issues, https://github.com/emanspeaks/pyrandyos/issues
Project-URL: Documentation, https://py.randyos.org
Author-email: Randy Eckman <emanspeaks@gmail.com>
Maintainer-email: Randy Eckman <emanspeaks@gmail.com>
License-Expression: MIT
License-File: LICENSE
Classifier: Operating System :: OS Independent
Classifier: Programming Language :: Python :: 3
Requires-Python: >=3.10
Requires-Dist: numpy
Requires-Dist: pandas
Requires-Dist: pyside2
Requires-Dist: pywin32; sys_platform == 'win32'
Requires-Dist: tqdm
Provides-Extra: dev
Requires-Dist: hatch-vcs; extra == 'dev'
Requires-Dist: hatchling; extra == 'dev'
Requires-Dist: pdoc; extra == 'dev'
Requires-Dist: types-pyside2; extra == 'dev'
Provides-Extra: qdarkstyle
Requires-Dist: qdarkstyle; extra == 'qdarkstyle'
